lsa_cli_smdmrr/__init__.py
lsa_cli_smdmrr/__main__.py
lsa_cli_smdmrr/annotation_parser.py
lsa_cli_smdmrr/annotations_to_entities_converter.py
lsa_cli_smdmrr/cli.py
lsa_cli_smdmrr/config.py
lsa_cli_smdmrr/models.py
lsa_cli_smdmrr/py.typed
lsa_cli_smdmrr/utils.py
lsa_cli_smdmrr/validator.py
lsa_cli-1.0.0.dist-info/LICENSE
lsa_cli-1.0.0.dist-info/METADATA
lsa_cli-1.0.0.dist-info/WHEEL
lsa_cli-1.0.0.dist-info/entry_points.txt
lsa_cli-1.0.0.dist-info/RECORD
