Metadata-Version: 2.1
Name: lsa-cli
Version: 1.0.0
Summary: CLI part of Linking Software Artifacts project
Author: Mark Seliverstov
Author-email: smdmrr00@gmail.com
Requires-Python: >=3.11,<4.0
Classifier: Programming Language :: Python :: 3
Classifier: Programming Language :: Python :: 3.11
Classifier: Programming Language :: Python :: 3.12
Classifier: Programming Language :: Python :: 3.13
Requires-Dist: comment-parser (>=1.2.4,<2.0.0)
Requires-Dist: structlog (>=24.4.0,<25.0.0)
